[
  {
    "root": "بِسْمِ",
    "meaning": "ابتداءً باسم الله"
  },
  {
    "root": "اللَّه",
    "meaning": "اسم الذات الإلهية"
  },
  {
    "root": "الرَّحْمَن",
    "meaning": "واسع الرحمة للخلق"
  },
  {
    "root": "الرَّحِيم",
    "meaning": "خاص الرحمة بالمؤمنين"
  },
  {
    "root": "رَبّ",
    "meaning": "المالك المربي السيد"
  },
  {
    "root": "عَالَمِين",
    "meaning": "جميع المخلوقات"
  },
  {
    "root": "يَوْم",
    "meaning": "من الفجر للغروب"
  },
  {
    "root": "دِين",
    "meaning": "الجزاء والمنهج"
  },
  {
    "root": "إِيَّاك",
    "meaning": "ضمير نصب للمخاطب"
  },
  {
    "root": "نَعْبُد",
    "meaning": "نُذِلّ ونخضع تعبداً"
  },
  {
    "root": "نَسْتَعِين",
    "meaning": "نطلب العون والمساعدة"
  },
  {
    "root": "اهْدِنَا",
    "meaning": "أرشدنا للطريق"
  },
  {
    "root": "صِرَاط",
    "meaning": "الطريق الواضح الواسع"
  },
  {
    "root": "مُسْتَقِيم",
    "meaning": "المعتدل بلا عِوَج"
  },
  {
    "root": "أَنْعَمْت",
    "meaning": "أنعمت عليهم"
  },
  {
    "root": "مَغْضُوب",
    "meaning": "الذين استحقوا الغضب"
  },
  {
    "root": "ضَالِّين",
    "meaning": "الذين ضلوا عن الحق"
  },
  {
    "root": "نُور",
    "meaning": "الضياء المزيل للظلام"
  },
  {
    "root": "حَمْد",
    "meaning": "الثناء على المنعم"
  },
  {
    "root": "مَلِك",
    "meaning": "صاحب السلطة"
  },
  {
    "root": "قُلْ",
    "meaning": "أمر بالقول"
  },
  {
    "root": "هُوَ",
    "meaning": "ضمير غائب مفرد"
  },
  {
    "root": "أَحَد",
    "meaning": "الواحد الفرد"
  },
  {
    "root": "صَمَد",
    "meaning": "الذي يُصمَد إليه"
  },
  {
    "root": "يَلِد",
    "meaning": "لم يُنجب أحداً"
  },
  {
    "root": "يُولَد",
    "meaning": "لم يُولد من أحد"
  },
  {
    "root": "كُفُوًا",
    "meaning": "المثيل والنظير"
  },
  {
    "root": "فَلَق",
    "meaning": "انشقاق الفجر"
  },
  {
    "root": "وَسْوَاس",
    "meaning": "إلقاء الشيطان في القلب"
  },
  {
    "root": "نَاس",
    "meaning": "بنو آدم جميعاً"
  },
  {
    "root": "إِيمَان",
    "meaning": "التصديق والإقرار والعمل"
  },
  {
    "root": "إِسْلَام",
    "meaning": "الاستسلام لله تعالى"
  },
  {
    "root": "إِحْسَان",
    "meaning": "العبادة بإتقان وإحسان"
  },
  {
    "root": "تَوْحِيد",
    "meaning": "إفراد الله بالعبادة"
  },
  {
    "root": "شِرْك",
    "meaning": "إشراك غير الله معه"
  },
  {
    "root": "كُفْر",
    "meaning": "جحود النعمة والكفر"
  },
  {
    "root": "نِفَاق",
    "meaning": "إظهار الإيمان وإخفاء الكفر"
  },
  {
    "root": "فُسُوق",
    "meaning": "الخروج عن حدود الشريعة"
  },
  {
    "root": "عِصْيَان",
    "meaning": "مخالفة أوامر الله"
  },
  {
    "root": "تَقْوَى",
    "meaning": "اتقاء عذاب الله بطاعته"
  },
  {
    "root": "وَرَع",
    "meaning": "التحرز من المحرمات"
  },
  {
    "root": "زُهْد",
    "meaning": "الزهد في زخرف الدنيا"
  },
  {
    "root": "رَحْمَة",
    "meaning": "الشفقة المؤدية للإحسان"
  },
  {
    "root": "صَبْر",
    "meaning": "حبس النفس عن الجزع"
  },
  {
    "root": "شُكْر",
    "meaning": "الاعتراف بالنعمة والثناء"
  },
  {
    "root": "تَوْبَة",
    "meaning": "الرجوع لله والندم"
  },
  {
    "root": "عَدْل",
    "meaning": "وضع الأمور في مواضعها"
  },
  {
    "root": "إِنصَاف",
    "meaning": "الإنصاف بين الناس"
  },
  {
    "root": "أَمَانَة",
    "meaning": "الوفاء بالعهد والأمانة"
  },
  {
    "root": "صِدْق",
    "meaning": "مطابقة الباطن للظاهر"
  },
  {
    "root": "وَفَاء",
    "meaning": "الوفاء بالعهود والمواثيق"
  },
  {
    "root": "حَيَاء",
    "meaning": "الاستحياء مما يُعاب"
  },
  {
    "root": "كَرَم",
    "meaning": "بذل العطاء بسخاء"
  },
  {
    "root": "عَفْو",
    "meaning": "التجاوز عن الذنب"
  },
  {
    "root": "حِلْم",
    "meaning": "الرفق والأناة في التعامل"
  },
  {
    "root": "تَوَاضُع",
    "meaning": "انكسار النفس لله"
  },
  {
    "root": "إِخْلَاص",
    "meaning": "إخلاص النية لله وحده"
  },
  {
    "root": "صَلَاة",
    "meaning": "العبادة ذات الأركان"
  },
  {
    "root": "زَكَاة",
    "meaning": "حق واجب في المال"
  },
  {
    "root": "صِيَام",
    "meaning": "الإمساك من الفجر للغروب"
  },
  {
    "root": "حَجّ",
    "meaning": "قصد البيت للمناسك"
  },
  {
    "root": "عُمْرَة",
    "meaning": "زيارة البيت خارج الحج"
  },
  {
    "root": "طَهَارَة",
    "meaning": "النظافة الشرعية الكاملة"
  },
  {
    "root": "وُضُوء",
    "meaning": "رفع الحدث الأصغر"
  },
  {
    "root": "غُسْل",
    "meaning": "رفع الحدث الأكبر"
  },
  {
    "root": "تَيَمُّم",
    "meaning": "التراب عند تعذر الماء"
  },
  {
    "root": "قِبْلَة",
    "meaning": "جهة الكعبة للصلاة"
  },
  {
    "root": "أَذَان",
    "meaning": "النداء لإعلام الصلاة"
  },
  {
    "root": "إِقَامَة",
    "meaning": "الإعلام بدخول وقت الصلاة"
  },
  {
    "root": "رَكْعَة",
    "meaning": "الصلاة من قيام وركوع وسجود"
  },
  {
    "root": "سُجُود",
    "meaning": "وضع الجبهة على الأرض"
  },
  {
    "root": "رُكُوع",
    "meaning": "الانحناء في الصلاة"
  },
  {
    "root": "قِيَام",
    "meaning": "الوقوف للصلاة"
  },
  {
    "root": "تَشَهُّد",
    "meaning": "الشهادتان في التشهد"
  },
  {
    "root": "سَلَام",
    "meaning": "إنهاء الصلاة بالسلام"
  },
  {
    "root": "جَنَّة",
    "meaning": "دار النعيم للمؤمنين"
  },
  {
    "root": "نَار",
    "meaning": "دار العقاب للكافرين"
  },
  {
    "root": "آخِرَة",
    "meaning": "الحياة بعد الموت"
  },
  {
    "root": "دُنْيَا",
    "meaning": "الحياة الزائلة الفانية"
  },
  {
    "root": "بَعْث",
    "meaning": "البعث من القبور"
  },
  {
    "root": "قِيَامَة",
    "meaning": "قيام الناس للحساب"
  },
  {
    "root": "حِسَاب",
    "meaning": "حساب الأعمال والنيات"
  },
  {
    "root": "مِيزَان",
    "meaning": "ميزان الحسنات والسيئات"
  },
  {
    "root": "صِرَاط",
    "meaning": "الجسر الممدود على جهنم"
  },
  {
    "root": "شَفَاعَة",
    "meaning": "طلب العفو لآخرين"
  },
  {
    "root": "كَوْثَر",
    "meaning": "نهر في الجنة للنبي"
  },
  {
    "root": "حُور",
    "meaning": "زوجات المؤمنين في الجنة"
  },
  {
    "root": "فِرْدَوْس",
    "meaning": "أعلى درجات الجنة"
  },
  {
    "root": "جَهَنَّم",
    "meaning": "النار العظيمة للكافرين"
  },
  {
    "root": "مَلَك",
    "meaning": "كائن نوراني مأمور"
  },
  {
    "root": "نَبِيّ",
    "meaning": "من أوحى إليه بشريعة"
  },
  {
    "root": "رَسُول",
    "meaning": "من أُرسِل للناس برسالة"
  },
  {
    "root": "صِدِّيق",
    "meaning": "الصادق الأكثر صدقاً"
  },
  {
    "root": "شَهِيد",
    "meaning": "الذي استشهد في سبيل الله"
  },
  {
    "root": "وَلِيّ",
    "meaning": "المقرب من الله"
  },
  {
    "root": "إِمَام",
    "meaning": "من يؤم الناس في الصلاة"
  },
  {
    "root": "عَالِم",
    "meaning": "العارف بأحكام الشريعة"
  },
  {
    "root": "جِبْرِيل",
    "meaning": "أمين الوحي الإلهي"
  },
  {
    "root": "مِيكَائِيل",
    "meaning": "الموكل بالأرزاق"
  },
  {
    "root": "إِسْرَافِيل",
    "meaning": "الموكل بالنفخ في الصور"
  },
  {
    "root": "إِبْلِيس",
    "meaning": "أبو الشياطين"
  },
  {
    "root": "شَيْطَان",
    "meaning": "الشيطان المغوي"
  },
  {
    "root": "جِنّ",
    "meaning": "خلق من نار مستترون"
  },
  {
    "root": "قُرْآن",
    "meaning": "كلام الله المنزل"
  },
  {
    "root": "سُورَة",
    "meaning": "طائفة من الآيات"
  },
  {
    "root": "آيَة",
    "meaning": "جملة قرآنية كاملة"
  },
  {
    "root": "حَدِيث",
    "meaning": "قول النبي أو فعله"
  },
  {
    "root": "سُنَّة",
    "meaning": "طريقة النبي وهديه"
  },
  {
    "root": "تَفْسِير",
    "meaning": "شرح معاني القرآن"
  },
  {
    "root": "تَجْوِيد",
    "meaning": "تحسين التلاوة بالأحكام"
  },
  {
    "root": "حِفْظ",
    "meaning": "استظهار القرآن عن ظهر قلب"
  },
  {
    "root": "تِلَاوَة",
    "meaning": "ترتيل الآيات وتدبرها"
  },
  {
    "root": "الغَفُور",
    "meaning": "الذي يغفر الذنوب كثيراً"
  },
  {
    "root": "القَدِير",
    "meaning": "الذي له القدرة التامة"
  },
  {
    "root": "العَلِيم",
    "meaning": "المحيط علمه بكل شيء"
  },
  {
    "root": "السَّمِيع",
    "meaning": "الذي يسمع كل شيء"
  },
  {
    "root": "البَصِير",
    "meaning": "الذي يرى كل شيء"
  },
  {
    "root": "الحَكِيم",
    "meaning": "الذي يضع الأمور مواضعها"
  },
  {
    "root": "الخَالِق",
    "meaning": "الذي أوجد الكون من عدم"
  },
  {
    "root": "الرَّزَّاق",
    "meaning": "الذي يرزق الخلق جميعاً"
  },
  {
    "root": "التَّوَّاب",
    "meaning": "الذي يقبل التوبة"
  },
  {
    "root": "الوَدُود",
    "meaning": "الذي يحب عباده المؤمنين"
  },
  {
    "root": "الصَّبُور",
    "meaning": "الذي يصبر على عباده"
  },
  {
    "root": "النُّور",
    "meaning": "نور السماوات والأرض"
  },
  {
    "root": "الحَيّ",
    "meaning": "الذي لا يموت"
  },
  {
    "root": "القَيُّوم",
    "meaning": "القائم بتدبير الخلق"
  },
  {
    "root": "الأَوَّل",
    "meaning": "الذي لا شيء قبله"
  },
  {
    "root": "الآخِر",
    "meaning": "الذي لا شيء بعده"
  },
  {
    "root": "الظَّاهِر",
    "meaning": "الظاهر بآياته وبراهينه"
  },
  {
    "root": "البَاطِن",
    "meaning": "العالم ببواطن الأمور"
  },
  {
    "root": "أُمَّة",
    "meaning": "جماعة الإسلام"
  },
  {
    "root": "عِلْم",
    "meaning": "إدراك الأشياء على حقيقتها"
  },
  {
    "root": "حَقّ",
    "meaning": "الصحيح الثابت الذي لا شك"
  },
  {
    "root": "خَيْر",
    "meaning": "ما يُرغب فيه ويُحمد"
  },
  {
    "root": "شَرّ",
    "meaning": "ما يُكره ويُذم"
  },
  {
    "root": "فِتْنَة",
    "meaning": "الابتلاء أو الفتنة بين الناس"
  },
  {
    "root": "بَلَاء",
    "meaning": "المصيبة والشدة"
  },
  {
    "root": "نِعْمَة",
    "meaning": "ما أنعم الله به على عبده"
  },
  {
    "root": "إِنسَان",
    "meaning": "الكائن البشري المكلف"
  },
  {
    "root": "رُوح",
    "meaning": "ما به الحياة والإدراك"
  },
  {
    "root": "عَقْل",
    "meaning": "القوة المدركة للحقائق"
  },
  {
    "root": "قَلْب",
    "meaning": "محل العقل والعاطفة"
  },
  {
    "root": "نَفْس",
    "meaning": "الذات أو جوهر الشيء"
  }
]